dccXMLJSONConv/__init__.py
dccXMLJSONConv/dccConv.py
dccXMLJSONConv/dccServer.py
dccXMLJSONConv/typeCastDictCreator.py
dccXMLJSONConv/data/__init__.py
dccXMLJSONConv/data/schemaTypeCastCache.json
dccXMLJSONConv-2.3.4.dist-info/LICENSE
dccXMLJSONConv-2.3.4.dist-info/METADATA
dccXMLJSONConv-2.3.4.dist-info/WHEEL
dccXMLJSONConv-2.3.4.dist-info/top_level.txt
dccXMLJSONConv-2.3.4.dist-info/RECORD
