Metadata-Version: 2.1
Name: dccXMLJSONConv
Version: 2.3.4
Summary: Python module for converting XML DCC (https://www.ptb.de/dcc/) to JSON and vice versa
Author: Benedikt Seeger,Thomas Bruns, Vanessa Stehr
Author-email: benedikt.seeger@ptb.de
License: LGPL-2.1-or-later
Requires-Python: >=3.10
License-File: LICENSE
Requires-Dist: jinja2
Requires-Dist: lxml
